runmonitor/__init__.py
runmonitor/check_daemon.py
runmonitor/check_effective_samples_error.py
runmonitor/check_error.py
runmonitor/check_tools.py
runmonitor/check_up.py
runmonitor/condor_tools.py
runmonitor/daemon_tools.py
runmonitor/dag_tools.py
runmonitor/dagpass.py
runmonitor/environ_check.py
runmonitor/force_pass.py
runmonitor/get_cluster.py
runmonitor/heal.py
runmonitor/rail_checker.py
runmonitor/report.py
runmonitor/restore.py
runmonitor/restore_tools.py
runmonitor/stat_rd.py
runmonitor/stat_tools.py
runmonitor/store_run.py
runmonitor/store_tools.py
runmonitor/test.py
runmonitor/update_archive.py
runmonitor/update_tools.py
runmonitor_RIFT-0.1.8.5.data/scripts/Plot Maker.py
runmonitor_RIFT-0.1.8.5.data/scripts/check_rift_analysis.sh
runmonitor_RIFT-0.1.8.5.data/scripts/create_new_run.sh
runmonitor_RIFT-0.1.8.5.data/scripts/event_report.sh
runmonitor_RIFT-0.1.8.5.data/scripts/event_runs.sh
runmonitor_RIFT-0.1.8.5.data/scripts/full_report.sh
runmonitor_RIFT-0.1.8.5.data/scripts/get_iteration.sh
runmonitor_RIFT-0.1.8.5.data/scripts/get_new_overflow.sh
runmonitor_RIFT-0.1.8.5.data/scripts/get_report.sh
runmonitor_RIFT-0.1.8.5.data/scripts/hcond.sh
runmonitor_RIFT-0.1.8.5.data/scripts/list_events.sh
runmonitor_RIFT-0.1.8.5.data/scripts/rail_checker.sh
runmonitor_RIFT-0.1.8.5.data/scripts/rmutil_check.py
runmonitor_RIFT-0.1.8.5.data/scripts/rmutil_daemon.py
runmonitor_RIFT-0.1.8.5.data/scripts/rmutil_dagpass.py
runmonitor_RIFT-0.1.8.5.data/scripts/rmutil_getcluster.py
runmonitor_RIFT-0.1.8.5.data/scripts/rmutil_getevents.py
runmonitor_RIFT-0.1.8.5.data/scripts/rmutil_report.py
runmonitor_RIFT-0.1.8.5.data/scripts/rmutil_restore.py
runmonitor_RIFT-0.1.8.5.data/scripts/rmutil_stat.py
runmonitor_RIFT-0.1.8.5.data/scripts/rmutil_store.py
runmonitor_RIFT-0.1.8.5.data/scripts/rmutil_update.py
runmonitor_RIFT-0.1.8.5.data/scripts/solve_cip_overflow.sh
runmonitor_RIFT-0.1.8.5.data/scripts/solve_frequency_error.sh
runmonitor_RIFT-0.1.8.5.data/scripts/solve_mc_range_error.sh
runmonitor_RIFT-0.1.8.5.dist-info/AUTHORS.md
runmonitor_RIFT-0.1.8.5.dist-info/LICENSE.md
runmonitor_RIFT-0.1.8.5.dist-info/METADATA
runmonitor_RIFT-0.1.8.5.dist-info/WHEEL
runmonitor_RIFT-0.1.8.5.dist-info/top_level.txt
runmonitor_RIFT-0.1.8.5.dist-info/RECORD
