Metadata-Version: 2.1
Name: runmonitor-RIFT
Version: 0.1.8.5
Summary: A package for monitoring RIFT PE runs
Home-page: https://git.ligo.org/richard.udall/runmonitor_rift
Author: Adhav Arulanandan, Grihith Manchanda, Richard O'Shaughnessy, Richard Udall, Joshua Brandt
Author-email: rudall@caltech.edu
License: UNKNOWN
Platform: UNKNOWN
Classifier: Programming Language :: Python :: 3.7
Classifier: License :: OSI Approved :: MIT License
Classifier: Operating System :: OS Independent
Requires-Python: >=3.7
Requires-Dist: python-daemon
Requires-Dist: setuptools
Requires-Dist: wheel
Requires-Dist: pip
